Selection_Method/Backward_Stepwise.py
Selection_Method/Forward_Stepwise.py
Selection_Method/__init__.py
Selection_Method-0.0.3.dist-info/LICENSE
Selection_Method-0.0.3.dist-info/METADATA
Selection_Method-0.0.3.dist-info/WHEEL
Selection_Method-0.0.3.dist-info/top_level.txt
Selection_Method-0.0.3.dist-info/RECORD
