Metadata-Version: 2.1
Name: Selection-Method
Version: 0.0.3
Summary: For selecting the optimal features using the stepwise algorithm
Home-page: https://github.com/dub-em/Selection-Methods-PythonTPL
Author: Dubem
Author-email: michaeligbomezie@gmail.com
Keywords: ["feature-selection","selection-methods","forward-stepwise","backward-stepwise","stepwise-selection","Dubem"]
Classifier: Programming Language :: Python :: 3
Classifier: License :: OSI Approved :: MIT License
Classifier: Operating System :: OS Independent
License-File: LICENSE
